duosida_ev/__init__.py
duosida_ev/charger.py
duosida_ev/cli.py
duosida_ev/discovery.py
duosida_ev/exceptions.py
duosida_ev-0.1.1.dist-info/METADATA
duosida_ev-0.1.1.dist-info/WHEEL
duosida_ev-0.1.1.dist-info/entry_points.txt
duosida_ev-0.1.1.dist-info/licenses/LICENSE
duosida_ev-0.1.1.dist-info/RECORD
