Metadata-Version: 2.4
Name: duosida-ev
Version: 0.1.1
Summary: Python library for direct TCP control of Duosida EV wall chargers
Project-URL: Homepage, https://github.com/americodias/duosida-ev
Project-URL: Repository, https://github.com/americodias/duosida-ev
Project-URL: Issues, https://github.com/americodias/duosida-ev/issues
Author-email: Americo Dias <americo.dias@gmail.com>
License: MIT
License-File: LICENSE
Keywords: charger,duosida,electric-vehicle,ev,iot,smart-home
Classifier: Development Status :: 4 - Beta
Classifier: Intended Audience :: Developers
Classifier: License :: OSI Approved :: MIT License
Classifier: Operating System :: OS Independent
Classifier: Programming Language :: Python :: 3
Classifier: Programming Language :: Python :: 3.6
Classifier: Programming Language :: Python :: 3.7
Classifier: Programming Language :: Python :: 3.8
Classifier: Programming Language :: Python :: 3.9
Classifier: Programming Language :: Python :: 3.10
Classifier: Programming Language :: Python :: 3.11
Classifier: Programming Language :: Python :: 3.12
Classifier: Topic :: Home Automation
Classifier: Topic :: Software Development :: Libraries :: Python Modules
Requires-Python: >=3.6
